realsense_cv2/__init__.py
realsense_cv2-0.0.1.dist-info/METADATA
realsense_cv2-0.0.1.dist-info/WHEEL
realsense_cv2-0.0.1.dist-info/top_level.txt
realsense_cv2-0.0.1.dist-info/RECORD
