Metadata-Version: 2.1
Name: realsense-cv2
Version: 0.0.1
Summary: A package to get opencv format image from realsense
Home-page: https://github.com/pypa/sampleproject
Author: Sam
Author-email: daisiran@emails.bjut.edu.cn
License: UNKNOWN
Platform: UNKNOWN
Classifier: Programming Language :: Python :: 3
Classifier: License :: OSI Approved :: MIT License
Classifier: Operating System :: OS Independent
